Workbook

Sheet Sales Log
A1: Order ID | B1: Date | C1: Product Name | D1: Category | E1: Units Sold | F1: Total Revenue | G1: COGS | H1: Supplier | I1: Supplier Email | J1: Gross Profit Margin %
A2: 1001 | B2: 46152 | C2: Gaming Monitor | D2: Screens | E2: 5 | F2: 1499.95 | G2: 600 | H2: =VLOOKUP(C2, 'Suppliers Catalog'!A$2:C$6,2,0) -> ScreenTech Ltd | I2: =VLOOKUP(C2 , 'Suppliers Catalog'!A$2:C$6 , 3 , 0) -> contact@screentech.com | J2: =(F2-G2)/F2 -> 0.59998667
A3: 1002 | B3: 46153 | C3: Mechanical Keyboard | D3: Accessories | E3: 10 | F3: 850 | G3: 340 | H3: =VLOOKUP(C3, 'Suppliers Catalog'!A$2:C$6,2,0) -> KeyClick Corp | I3: =VLOOKUP(C3 , 'Suppliers Catalog'!A$2:C$6 , 3 , 0) -> sales@keyclick.com | J3: =(F3-G3)/F3 -> 0.6
A4: 1003 | B4: 46153 | C4: USB-C Cable | D4: Cables | E4: 50 | F4: 625 | G4: 250 | H4: =VLOOKUP(C4, 'Suppliers Catalog'!A$2:C$6,2,0) -> LinkWire Solutions | I4: =VLOOKUP(C4 , 'Suppliers Catalog'!A$2:C$6 , 3 , 0) -> info@linkwire.com | J4: =(F4-G4)/F4 -> 0.6
A5: 1004 | B5: 46154 | C5: Wireless Mouse | D5: Accessories | E5: 20 | F5: 500 | G5: 200 | H5: =VLOOKUP(C5, 'Suppliers Catalog'!A$2:C$6,2,0) -> GoWireless Co | I5: =VLOOKUP(C5 , 'Suppliers Catalog'!A$2:C$6 , 3 , 0) -> support@gowireless.com | J5: =(F5-G5)/F5 -> 0.6
A6: 1005 | B6: 46155 | C6: Gaming Monitor | D6: Screens | E6: 2 | F6: 599.94 | G6: 240 | H6: =VLOOKUP(C6, 'Suppliers Catalog'!A$2:C$6,2,0) -> ScreenTech Ltd | I6: =VLOOKUP(C6 , 'Suppliers Catalog'!A$2:C$6 , 3 , 0) -> contact@screentech.com | J6: =(F6-G6)/F6 -> 0.59996
A7: 1006 | B7: 46156 | C7: Bluetooth Speaker | D7: Audio | E7: 15 | F7: 1200 | G7: 480 | H7: =VLOOKUP(C7, 'Suppliers Catalog'!A$2:C$6,2,0) -> SoundWave Inc | I7: =VLOOKUP(C7 , 'Suppliers Catalog'!A$2:C$6 , 3 , 0) -> orders@soundwave.com | J7: =(F7-G7)/F7 -> 0.6
A8: 1007 | B8: 46157 | C8: Mechanical Keyboard | D8: Accessories | E8: 4 | F8: 340 | G8: 136 | H8: =VLOOKUP(C8, 'Suppliers Catalog'!A$2:C$6,2,0) -> KeyClick Corp | I8: =VLOOKUP(C8 , 'Suppliers Catalog'!A$2:C$6 , 3 , 0) -> sales@keyclick.com | J8: =(F8-G8)/F8 -> 0.6
A9: 1008 | B9: 46158 | C9: USB-C Cable | D9: Cables | E9: 30 | F9: 375 | G9: 150 | H9: =VLOOKUP(C9, 'Suppliers Catalog'!A$2:C$6,2,0) -> LinkWire Solutions | I9: =VLOOKUP(C9 , 'Suppliers Catalog'!A$2:C$6 , 3 , 0) -> info@linkwire.com | J9: =(F9-G9)/F9 -> 0.6
A10: 1009 | B10: 46159 | C10: Wireless Mouse | D10: Accessories | E10: 12 | F10: 300 | G10: 120 | H10: =VLOOKUP(C10, 'Suppliers Catalog'!A$2:C$6,2,0) -> GoWireless Co | I10: =VLOOKUP(C10 , 'Suppliers Catalog'!A$2:C$6 , 3 , 0) -> support@gowireless.com | J10: =(F10-G10)/F10 -> 0.6
A11: 1010 | B11: 46160 | C11: Bluetooth Speaker | D11: Audio | E11: 8 | F11: 640 | G11: 256 | H11: =VLOOKUP(C11, 'Suppliers Catalog'!A$2:C$6,2,0) -> SoundWave Inc | I11: =VLOOKUP(C11 , 'Suppliers Catalog'!A$2:C$6 , 3 , 0) -> orders@soundwave.com | J11: =(F11-G11)/F11 -> 0.6
A12: 1011 | B12: 46161 | C12: USB-C Cable | D12: Cables | E12: 15 | F12: 187.5 | G12: 75 | H12: =VLOOKUP(C12, 'Suppliers Catalog'!A$2:C$6,2,0) -> LinkWire Solutions | I12: =VLOOKUP(C12 , 'Suppliers Catalog'!A$2:C$6 , 3 , 0) -> info@linkwire.com | J12: =(F12-G12)/F12 -> 0.6

Sheet Supplier Performance

Sheet Category Analysis

Sheet Suppliers Catalog
A1: Product Name | B1: Supplier | C1: Supplier Email
A2: Gaming Monitor | B2: ScreenTech Ltd | C2: contact@screentech.com
A3: Mechanical Keyboard | B3: KeyClick Corp | C3: sales@keyclick.com
A4: USB-C Cable | B4: LinkWire Solutions | C4: info@linkwire.com
A5: Wireless Mouse | B5: GoWireless Co | C5: support@gowireless.com
A6: Bluetooth Speaker | B6: SoundWave Inc | C6: orders@soundwave.com
